managementtools/__init__.py
managementtools/management/__init__.py
managementtools/management/commands/__init__.py
managementtools/management/commands/createadmin.py
django_management_tools-0.2.2.dist-info/LICENSE
django_management_tools-0.2.2.dist-info/METADATA
django_management_tools-0.2.2.dist-info/WHEEL
django_management_tools-0.2.2.dist-info/top_level.txt
django_management_tools-0.2.2.dist-info/RECORD
