Metadata-Version: 2.1
Name: django-management-tools
Version: 0.2.2
Summary: Commands to extend Django's manage.py functionality
Home-page: https://gitlab.com/pennatus/django-management-tools
Author: Steve Graham
Author-email: stgraham2000@gmail.com
License: MIT license
Keywords: django-management-tools
Platform: UNKNOWN
Classifier: Development Status :: 2 - Pre-Alpha
Classifier: Intended Audience :: Developers
Classifier: License :: OSI Approved :: MIT License
Classifier: Natural Language :: English
Classifier: Programming Language :: Python :: 2
Classifier: Programming Language :: Python :: 2.7
Classifier: Programming Language :: Python :: 3
Classifier: Programming Language :: Python :: 3.5
Classifier: Programming Language :: Python :: 3.6
Classifier: Programming Language :: Python :: 3.7
Classifier: Programming Language :: Python :: 3.8
Requires-Python: >=2.7, !=3.0.*, !=3.1.*, !=3.2.*, !=3.3.*, !=3.4.*
Requires-Dist: hvac (>=0.9.5)
Requires-Dist: requests (>=2.22.0)
